[
    {
        "name": "Adriano",
        "date": "12. September 2022",
        "time": "19:49:07",
        "late": true,
        "order": 1
    },
    {
        "name": "Adriano",
        "date": "12. September 2022",
        "time": "19:49:11",
        "late": true,
        "order": 2
    },
    {
        "name": "Adriano",
        "date": "12. September 2022",
        "time": "19:49:22",
        "late": true,
        "order": 3
    },
    {
        "name": "Adriano",
        "date": "12. September 2022",
        "time": "19:49:24",
        "late": true,
        "order": 4
    }
]